<?xml version='1.0' encoding='UTF-8'?>
<root BTCPP_format="4" main_tree_to_execute="Grasp Pose Griz Tuning to Yaml">
  <!--//////////-->
  <BehaviorTree ID="Grasp Pose Griz Tuning to Yaml" _description="Moves the gripper to the April Tag and then prompts the user to teleop to a grasp pose. Saves the resulting pose to a YAML file." _favorite="false">
    <Control ID="Sequence" name="TopLevelSequence">
      <SubTree ID="Request Teleoperation" _collapsed="true" enable_user_interaction="true" initial_teleop_mode="3" user_interaction_prompt="Teleoperate end effector to grasp pose"/>
      <SubTree ID="Get Transform Frame Pose" _collapsed="true" requested_pose="{grasp_pose}" requested_frame="grasp_link"/>
      <Action ID="SavePoseStampedToYaml" message="{grasp_pose}" yaml_filename="griz_grasp_pose" namespace="GraspPose2"/>
    </Control>
  </BehaviorTree>
  <TreeNodesModel>
    <SubTree ID="Grasp Pose Griz Tuning to Yaml">
      <MetadataFields>
        <Metadata subcategory="Application - Advanced Examples"/>
        <Metadata runnable="true"/>
      </MetadataFields>
    </SubTree>
  </TreeNodesModel>
</root>
